sksurgerybk/__init__.py
sksurgerybk/__main__.py
sksurgerybk/_version.py
sksurgerybk/interface/__init__.py
sksurgerybk/interface/bk5000.py
sksurgerybk/pyigtlink/__init__.py
sksurgerybk/pyigtlink/pyIGTLink.py
scikit_surgerybk-0.3.3.dist-info/LICENSE
scikit_surgerybk-0.3.3.dist-info/METADATA
scikit_surgerybk-0.3.3.dist-info/WHEEL
scikit_surgerybk-0.3.3.dist-info/entry_points.txt
scikit_surgerybk-0.3.3.dist-info/top_level.txt
scikit_surgerybk-0.3.3.dist-info/RECORD
